{
  "uoa" : "vscaladoc2_demoprj/0.1-SNAPSHOT/itest.demo1/DemoC",
  "e" : [ {
    "name" : "DemoC",
    "qualifiedName" : "itest.demo1.DemoC",
    "definitionName" : "itest.demo1.DemoC",
    "description" : "<p>Doc of DemoC (object)\n....\n</p>",
    "docTags" : [ ],
    "flags" : "Public()",
    "inheritedFrom" : [ ],
    "visibility" : [ ],
    "resultType" : [ [ "DemoC", "vscaladoc2_demoprj/0.1-SNAPSHOT/itest.demo1/DemoC" ] ],
    "sourceStartPoint" : [ "/home/dwayne/work/oss/vscaladoc2_demoprj/src/main/scala/itest/demo1/DemoC.scala", 11 ],
    "subClassesK" : [ ],
    "members" : [ "scala-library/2.8.0/scala/Any/1.DemoC$hash$bang$eq", "scala-library/2.8.0/scala/Any/1.DemoC$hash$eq$eq", "scala-library/2.8.0/scala/Any/1.DemoC$hashasInstanceOf", "scala-library/2.8.0/scala/Any/1.DemoC$hashisInstanceOf", "scala-library/2.8.0/scala/AnyRef/emoC$hash$asInstanceOf", "scala-library/2.8.0/scala/AnyRef/emoC$hash$bang$eq", "scala-library/2.8.0/scala/AnyRef/emoC$hash$eq$eq", "scala-library/2.8.0/scala/AnyRef/emoC$hash$hash$hash", "scala-library/2.8.0/scala/AnyRef/emoC$hash$isInstanceOf", "scala-library/2.8.0/scala/AnyRef/emoC$hashclone", "scala-library/2.8.0/scala/AnyRef/emoC$hasheq", "scala-library/2.8.0/scala/AnyRef/emoC$hashequals", "scala-library/2.8.0/scala/AnyRef/emoC$hashfinalize", "scala-library/2.8.0/scala/AnyRef/emoC$hashgetClass", "scala-library/2.8.0/scala/AnyRef/emoC$hashhashCode", "scala-library/2.8.0/scala/AnyRef/emoC$hashne", "scala-library/2.8.0/scala/AnyRef/emoC$hashnotify", "scala-library/2.8.0/scala/AnyRef/emoC$hashnotifyAll", "scala-library/2.8.0/scala/AnyRef/emoC$hashsynchronized", "scala-library/2.8.0/scala/AnyRef/emoC$hashtoString", "scala-library/2.8.0/scala/AnyRef/emoC$hashwait", "vscaladoc2_demoprj/0.1-SNAPSHOT/itest.demo1/DemoC/ctorArg2", "vscaladoc2_demoprj/0.1-SNAPSHOT/itest.demo1/DemoC/doStuff", "vscaladoc2_demoprj/0.1-SNAPSHOT/itest.demo1/DemoC/methodDeprecatedByAnnot", "vscaladoc2_demoprj/0.1-SNAPSHOT/itest.demo1/DemoC/methodDeprecatedByDoc" ],
    "templates" : [ ],
    "methods" : [ "scala-library/2.8.0/scala/Any/1.DemoC$hash$bang$eq", "scala-library/2.8.0/scala/Any/1.DemoC$hash$eq$eq", "scala-library/2.8.0/scala/Any/1.DemoC$hashasInstanceOf", "scala-library/2.8.0/scala/Any/1.DemoC$hashisInstanceOf", "scala-library/2.8.0/scala/AnyRef/emoC$hash$asInstanceOf", "scala-library/2.8.0/scala/AnyRef/emoC$hash$bang$eq", "scala-library/2.8.0/scala/AnyRef/emoC$hash$eq$eq", "scala-library/2.8.0/scala/AnyRef/emoC$hash$hash$hash", "scala-library/2.8.0/scala/AnyRef/emoC$hash$isInstanceOf", "scala-library/2.8.0/scala/AnyRef/emoC$hashclone", "scala-library/2.8.0/scala/AnyRef/emoC$hasheq", "scala-library/2.8.0/scala/AnyRef/emoC$hashequals", "scala-library/2.8.0/scala/AnyRef/emoC$hashfinalize", "scala-library/2.8.0/scala/AnyRef/emoC$hashgetClass", "scala-library/2.8.0/scala/AnyRef/emoC$hashhashCode", "scala-library/2.8.0/scala/AnyRef/emoC$hashne", "scala-library/2.8.0/scala/AnyRef/emoC$hashnotify", "scala-library/2.8.0/scala/AnyRef/emoC$hashnotifyAll", "scala-library/2.8.0/scala/AnyRef/emoC$hashsynchronized", "scala-library/2.8.0/scala/AnyRef/emoC$hashtoString", "scala-library/2.8.0/scala/AnyRef/emoC$hashwait", "vscaladoc2_demoprj/0.1-SNAPSHOT/itest.demo1/DemoC/doStuff", "vscaladoc2_demoprj/0.1-SNAPSHOT/itest.demo1/DemoC/methodDeprecatedByAnnot", "vscaladoc2_demoprj/0.1-SNAPSHOT/itest.demo1/DemoC/methodDeprecatedByDoc" ],
    "values" : [ "vscaladoc2_demoprj/0.1-SNAPSHOT/itest.demo1/DemoC/ctorArg2" ],
    "abstractTypes" : [ ],
    "aliasTypes" : [ ],
    "companion" : "vscaladoc2_demoprj/0.1-SNAPSHOT/itest.demo1/DemoC",
    "parentType" : [ [ "DemoC", "vscaladoc2_demoprj/0.1-SNAPSHOT/itest.demo1/DemoC" ], [ "[" ], [ "String", "jse/1.6.0_22/java.lang/String" ], [ "]" ] ],
    "linearization" : [ "vscaladoc2_demoprj/0.1-SNAPSHOT/itest.demo1/DemoC", "scala-library/2.8.0/scala/AnyRef", "scala-library/2.8.0/scala/Any" ],
    "kind" : "object"
  }, {
    "name" : "DemoC",
    "qualifiedName" : "itest.demo1.DemoC",
    "definitionName" : "itest.demo1.DemoC",
    "description" : "<p>Class use to test override, inheritance,... (with object DemoC and child class DemoC2)\n</p>",
    "docTags" : [ ],
    "flags" : "Public()",
    "inheritedFrom" : [ ],
    "visibility" : [ ],
    "resultType" : [ [ "DemoC", "vscaladoc2_demoprj/0.1-SNAPSHOT/itest.demo1/DemoC" ], [ "[T]" ] ],
    "sourceStartPoint" : [ "/home/dwayne/work/oss/vscaladoc2_demoprj/src/main/scala/itest/demo1/DemoC.scala", 16 ],
    "subClassesK" : [ "vscaladoc2_demoprj/0.1-SNAPSHOT/itest.demo1/DemoC", "vscaladoc2_demoprj/0.1-SNAPSHOT/itest.demo1/DemoC2" ],
    "members" : [ "scala-library/2.8.0/scala/Any/1.DemoC$hash$bang$eq", "scala-library/2.8.0/scala/Any/1.DemoC$hash$eq$eq", "scala-library/2.8.0/scala/Any/1.DemoC$hashasInstanceOf", "scala-library/2.8.0/scala/Any/1.DemoC$hashisInstanceOf", "scala-library/2.8.0/scala/AnyRef/emoC$hash$asInstanceOf", "scala-library/2.8.0/scala/AnyRef/emoC$hash$bang$eq", "scala-library/2.8.0/scala/AnyRef/emoC$hash$eq$eq", "scala-library/2.8.0/scala/AnyRef/emoC$hash$hash$hash", "scala-library/2.8.0/scala/AnyRef/emoC$hash$isInstanceOf", "scala-library/2.8.0/scala/AnyRef/emoC$hashclone", "scala-library/2.8.0/scala/AnyRef/emoC$hasheq", "scala-library/2.8.0/scala/AnyRef/emoC$hashequals", "scala-library/2.8.0/scala/AnyRef/emoC$hashfinalize", "scala-library/2.8.0/scala/AnyRef/emoC$hashgetClass", "scala-library/2.8.0/scala/AnyRef/emoC$hashhashCode", "scala-library/2.8.0/scala/AnyRef/emoC$hashne", "scala-library/2.8.0/scala/AnyRef/emoC$hashnotify", "scala-library/2.8.0/scala/AnyRef/emoC$hashnotifyAll", "scala-library/2.8.0/scala/AnyRef/emoC$hashsynchronized", "scala-library/2.8.0/scala/AnyRef/emoC$hashtoString", "scala-library/2.8.0/scala/AnyRef/emoC$hashwait", "vscaladoc2_demoprj/0.1-SNAPSHOT/itest.demo1/DemoC/ctorArg2", "vscaladoc2_demoprj/0.1-SNAPSHOT/itest.demo1/DemoC/doStuff", "vscaladoc2_demoprj/0.1-SNAPSHOT/itest.demo1/DemoC/methodDeprecatedByAnnot", "vscaladoc2_demoprj/0.1-SNAPSHOT/itest.demo1/DemoC/methodDeprecatedByDoc", "vscaladoc2_demoprj/0.1-SNAPSHOT/itest.demo1/DemoC/this" ],
    "templates" : [ ],
    "methods" : [ "scala-library/2.8.0/scala/Any/1.DemoC$hash$bang$eq", "scala-library/2.8.0/scala/Any/1.DemoC$hash$eq$eq", "scala-library/2.8.0/scala/Any/1.DemoC$hashasInstanceOf", "scala-library/2.8.0/scala/Any/1.DemoC$hashisInstanceOf", "scala-library/2.8.0/scala/AnyRef/emoC$hash$asInstanceOf", "scala-library/2.8.0/scala/AnyRef/emoC$hash$bang$eq", "scala-library/2.8.0/scala/AnyRef/emoC$hash$eq$eq", "scala-library/2.8.0/scala/AnyRef/emoC$hash$hash$hash", "scala-library/2.8.0/scala/AnyRef/emoC$hash$isInstanceOf", "scala-library/2.8.0/scala/AnyRef/emoC$hashclone", "scala-library/2.8.0/scala/AnyRef/emoC$hasheq", "scala-library/2.8.0/scala/AnyRef/emoC$hashequals", "scala-library/2.8.0/scala/AnyRef/emoC$hashfinalize", "scala-library/2.8.0/scala/AnyRef/emoC$hashgetClass", "scala-library/2.8.0/scala/AnyRef/emoC$hashhashCode", "scala-library/2.8.0/scala/AnyRef/emoC$hashne", "scala-library/2.8.0/scala/AnyRef/emoC$hashnotify", "scala-library/2.8.0/scala/AnyRef/emoC$hashnotifyAll", "scala-library/2.8.0/scala/AnyRef/emoC$hashsynchronized", "scala-library/2.8.0/scala/AnyRef/emoC$hashtoString", "scala-library/2.8.0/scala/AnyRef/emoC$hashwait", "vscaladoc2_demoprj/0.1-SNAPSHOT/itest.demo1/DemoC/doStuff", "vscaladoc2_demoprj/0.1-SNAPSHOT/itest.demo1/DemoC/methodDeprecatedByAnnot", "vscaladoc2_demoprj/0.1-SNAPSHOT/itest.demo1/DemoC/methodDeprecatedByDoc" ],
    "values" : [ "vscaladoc2_demoprj/0.1-SNAPSHOT/itest.demo1/DemoC/ctorArg2" ],
    "abstractTypes" : [ ],
    "aliasTypes" : [ ],
    "companion" : "vscaladoc2_demoprj/0.1-SNAPSHOT/itest.demo1/DemoC",
    "parentType" : [ [ "AnyRef" ] ],
    "linearization" : [ "scala-library/2.8.0/scala/AnyRef", "scala-library/2.8.0/scala/Any" ],
    "typeParams" : [ [ "[" ], [ "T" ], [ "]" ] ],
    "isCaseClass" : false,
    "constructors" : [ {
      "name" : "this",
      "qualifiedName" : "itest.demo1.DemoC#this",
      "definitionName" : "itest.demo1.DemoC#this",
      "flags" : "Public()",
      "inheritedFrom" : [ ],
      "visibility" : [ ],
      "resultType" : [ [ "DemoC", "vscaladoc2_demoprj/0.1-SNAPSHOT/itest.demo1/DemoC" ], [ "[T]" ] ],
      "valueParams" : [ [ "( " ], [ "ctorArg1 : " ], [ "Int", "scala-library/2.8.0/scala/Int" ], [ ", " ], [ "ctorArg2 : " ], [ "String", "jse/1.6.0_22/java.lang/String" ], [ ", " ], [ "ctorArg3 : " ], [ "T" ], [ " )" ] ],
      "isPrimary" : true,
      "kind" : "def"
    } ],
    "kind" : "class"
  } ]
}